postocr_3stages/NMT_corrector.py
postocr_3stages/__init__.py
postocr_3stages/controller.py
postocr_3stages/error_detector.py
postocr_3stages/icdar_utils.py
postocr_3stages/pipeline.py
postocr_3stages/utils.py
postocr_3stages-0.1.0.dist-info/LICENSE
postocr_3stages-0.1.0.dist-info/METADATA
postocr_3stages-0.1.0.dist-info/WHEEL
postocr_3stages-0.1.0.dist-info/RECORD
