Metadata-Version: 2.1
Name: postocr-3stages
Version: 0.1.0
Summary: Post-OCR correction in 3 stages.
Home-page: https://github.com/soduco/postocr-3stages
License: GPL
Author: EPITA Research Lab
Author-email: contact@lre.epita.fr
Requires-Python: >=3.8,<3.11
Classifier: License :: Other/Proprietary License
Classifier: Programming Language :: Python :: 3
Classifier: Programming Language :: Python :: 3.8
Classifier: Programming Language :: Python :: 3.9
Classifier: Programming Language :: Python :: 3.10
Requires-Dist: OpenNMT-py (>=3.0.4,<4.0.0)
Requires-Dist: accelerate (>=0.20.1)
Requires-Dist: cer (>=1.2.0,<2.0.0)
Requires-Dist: datasets (>=2.10.1,<3.0.0)
Requires-Dist: evaluate (>=0.4.0,<0.5.0)
Requires-Dist: jiwer (>=2.5.1,<3.0.0)
Requires-Dist: matplotlib (>=3.5.3,<4.0.0)
Requires-Dist: numpy (>=1.22.4,<2.0.0)
Requires-Dist: pandas (>=1.3.5,<2.0.0)
Requires-Dist: pybind11 (>=2.10.3,<3.0.0)
Requires-Dist: scikit-learn (>=1.0.2,<2.0.0)
Requires-Dist: sentencepiece (>=0.1.97,<0.2.0)
Requires-Dist: torch (>=1.13.0,<2.0.0)
Requires-Dist: tqdm (>=4.64.1,<5.0.0)
Requires-Dist: transformers (>=4.26.1,<5.0.0)
Project-URL: Repository, https://github.com/soduco/postocr-3stages
